{
  "type": "panel",
  "name": "Track Map",
  "id": "alexandra-trackmap-panel",
  "info": {
    "description": "A map plugin to visualise GPS data as markers, hexbin, ant path, or heatmap",
    "author": {
      "name": "Alexandra Institute",
      "url": "https://alexandra.dk/"
    },
    "keywords": [
      "map",
      "tracking",
      "time",
      "markers",
      "ant path",
      "heatmap",
      "hexbin"
    ],
    "logos": {
      "small": "img/logo.svg",
      "large": "img/logo.svg"
    },
    "links": [
      {"name": "Project site", "url": "https://github.com/alexandrainst/alexandra-trackmap-panel"},
      {"name": "MIT License", "url": "https://github.com/alexandrainst/alexandra-trackmap-panel/blob/master/LICENSE"}
    ],
    "screenshots": [],
    "version": "2.0.1",
    "updated": "2020-10-31"
  },
  "dependencies": {
    "grafanaVersion": "7.x.x",
    "plugins": []
  }
}